hh_applicant_tool/__init__.py
hh_applicant_tool/__main__.py
hh_applicant_tool/ai/__init__.py
hh_applicant_tool/ai/base.py
hh_applicant_tool/ai/openai.py
hh_applicant_tool/api/__init__.py
hh_applicant_tool/api/client.py
hh_applicant_tool/api/client_keys.py
hh_applicant_tool/api/datatypes.py
hh_applicant_tool/api/errors.py
hh_applicant_tool/api/user_agent.py
hh_applicant_tool/main.py
hh_applicant_tool/operations/__init__.py
hh_applicant_tool/operations/apply_similar.py
hh_applicant_tool/operations/authorize.py
hh_applicant_tool/operations/call_api.py
hh_applicant_tool/operations/check_proxy.py
hh_applicant_tool/operations/clear_negotiations.py
hh_applicant_tool/operations/clone_resume.py
hh_applicant_tool/operations/config.py
hh_applicant_tool/operations/install.py
hh_applicant_tool/operations/list_resumes.py
hh_applicant_tool/operations/log.py
hh_applicant_tool/operations/logout.py
hh_applicant_tool/operations/migrate_db.py
hh_applicant_tool/operations/query.py
hh_applicant_tool/operations/refresh_token.py
hh_applicant_tool/operations/reply_employers.py
hh_applicant_tool/operations/settings.py
hh_applicant_tool/operations/uninstall.py
hh_applicant_tool/operations/update_resumes.py
hh_applicant_tool/operations/whoami.py
hh_applicant_tool/storage/__init__.py
hh_applicant_tool/storage/facade.py
hh_applicant_tool/storage/models/__init__.py
hh_applicant_tool/storage/models/base.py
hh_applicant_tool/storage/models/contacts.py
hh_applicant_tool/storage/models/employer.py
hh_applicant_tool/storage/models/negotiation.py
hh_applicant_tool/storage/models/resume.py
hh_applicant_tool/storage/models/setting.py
hh_applicant_tool/storage/models/vacancy.py
hh_applicant_tool/storage/queries/migrations/.gitkeep
hh_applicant_tool/storage/queries/schema.sql
hh_applicant_tool/storage/repositories/__init__.py
hh_applicant_tool/storage/repositories/base.py
hh_applicant_tool/storage/repositories/contacts.py
hh_applicant_tool/storage/repositories/employers.py
hh_applicant_tool-1.5.13.dist-info/METADATA
hh_applicant_tool-1.5.13.dist-info/WHEEL
hh_applicant_tool-1.5.13.dist-info/entry_points.txt
hh_applicant_tool-1.5.13.dist-info/RECORD
