Metadata-Version: 2.4
Name: hh-applicant-tool
Version: 1.5.13
Summary: HH-Applicant-Tool: An automation utility for HeadHunter (hh.ru) designed to streamline the job search process by auto-applying to relevant vacancies and periodically refreshing resumes to stay at the top of recruiter searches.
Author: Senior YAML Developer
Author-email: yamldeveloper@proton.me
Requires-Python: >=3.10,<4.0
Classifier: Programming Language :: Python :: 3
Classifier: Programming Language :: Python :: 3.10
Classifier: Programming Language :: Python :: 3.11
Classifier: Programming Language :: Python :: 3.12
Classifier: Programming Language :: Python :: 3.13
Classifier: Programming Language :: Python :: 3.14
Provides-Extra: pillow
Provides-Extra: playwright
Requires-Dist: pillow (>=12.1.0,<13.0.0) ; extra == "pillow"
Requires-Dist: playwright (>=1.57.0,<2.0.0) ; extra == "playwright"
Requires-Dist: prettytable (>=3.6.0,<4.0.0)
Requires-Dist: requests[socks] (>=2.32.3,<3.0.0)
Project-URL: Homepage, https://github.com/s3rgeym/hh-applicant-tool
Project-URL: Repository, https://github.com/s3rgeym/hh-applicant-tool
